{
  "transactions": [
    {
      "id": "1",
      "description": "Salário",
      "type": "income",
      "category": "Desenvolvimento",
      "amount": 6000,
      "createdAt": "2024-12-25T19:30:45.754Z"
    },
    {
      "id": "d6ce",
      "amount": 6000,
      "category": "Desenvolvimento",
      "description": "Salário",
      "type": "income",
      "createdAt": "2024-12-29T21:36:11.246Z"
    },
    {
      "id": "9afd",
      "amount": 25,
      "category": "Alimentação",
      "description": "Hamburguer",
      "type": "outcome",
      "createdAt": "2024-12-29T21:37:54.835Z"
    },
    {
      "id": "1b88",
      "amount": 6000,
      "category": "Desenvolvimento",
      "description": "Salario",
      "type": "income",
      "createdAt": "2024-12-29T21:51:07.236Z"
    },
    {
      "id": "ee19",
      "amount": 17,
      "category": "Alimentação",
      "description": "Açai",
      "type": "outcome",
      "createdAt": "2024-12-29T21:52:12.438Z"
    },
    {
      "id": "b6ef",
      "amount": 6000,
      "category": "Desenvolvimento",
      "description": "Salário",
      "type": "income",
      "createdAt": "2025-01-09T10:54:52.980Z"
    }
  ]
}